last.py
main.py
try.py
workbench.py
chromedriver/__init__.py
chromedriver/chromedriver-linux64.zip
chromedriver/chromedriver-win64.zip
oss_zhao_2025-0.0.3.dist-info/METADATA
oss_zhao_2025-0.0.3.dist-info/WHEEL
oss_zhao_2025-0.0.3.dist-info/top_level.txt
oss_zhao_2025-0.0.3.dist-info/RECORD
