Metadata-Version: 2.1
Name: oss-zhao-2025
Version: 0.0.3
Author: zhao
Requires-Python: >=3.8
Requires-Dist: selenium==4.27.1
Requires-Dist: beautifulsoup4==4.9.1
